{"author": "","hits": "281","cited": "52","refs": "1","label": "DiffBind",			"summary": ["Differential Binding Analysis of ChIP-Seq peak data\nCompute differentially bound sites from multiple ChIP-seq experiments using affinity (quantitative) data. Also enables occupancy (overlap) analysis and plotting functions."],			"bio_tags": ["ChIP-Seq"],			"meth_tags": ["Differential binding sites"],			"features": ["Multiple replicates information used; automated pipeline; finding hotspots;"],			"language": ["R"],			"licence": ["Artistic-2.0"],			"os": ["Linux","Mac OS X","Windows"]		}