{"author": "","hits": "2686","cited": "53","refs": "1","label": "Ibis",			"summary": ["Ibis (Improved base identification system), is an accurate, fast and easy-to-use base caller for the Illumina sequencing system, which significantly reduces the error rate and increases the output of usable reads. Ibis is faster and makes fewer assumptions about chemistry and technology"],			"bio_tags": ["Sequencing"],			"meth_tags": ["Basecaller"],			"features": ["Statistical learning of base calling parameters and calibrated quality scoring"],			"language": ["Python","C","C++"],			"licence": ["Non-commercial"],			"os": ["Linux","Windows (Cygwin)"]		}